{
   "flag":"pl.png",
   "name":"Polish",
   "strings":{
      "home":{
         "other_links":{
            
         },
         "sub_header":"Ostatnio obrabiane bloki w łańcuchu bloków bitcoin",
         "table_headers":{
            "sent":"Razem wysłanych"
         },
         "about":{
            
         }
      },
      "connected_nodes":{
         
      },
      "popular_addresses":{
         
      },
      "orphaned_blocks":{
         
      },
      "api_index":{
         "request_limits_p1":"lub Kod API ominąć wniosek limiter proszę",
         "websocket_description":"Małe opóźnienie kanału gniazdo strumieniowe dostarczanie danych na temat nowych bloków i transakcji. Zapisz się na powiadomienia o blokach, transakcji lub adres i odbieranie obiekty JSON opisujące transakcji lub blokady, gdy wystąpi zdarzenie.",
         "receive_payments_description":"Niesamowite łatwy sposób na stronach internetowych w celu przyjmowania płatności Bitcoin."
      },
      "deposit":{
         
      },
      "transaction":{
         
      },
      "stats":{
         "table":{
            
         }
      },
      "block":{
         "hash_table":{
            
         },
         "summary_table":{
            "output_title":"Tytuł Output"
         }
      },
      "ip_info":{
         
      },
      "double_spends":{
         
      },
      "wallet_app":{
         "transactions":{
            
         },
         "errors":{
            "mobile_identifier_not_found":"Portfel identyfikator nie znaleziono. Twój portfel nie jest jeszcze zapisany na naszym serwerze, jeszcze. Proszę skonfigurować nowe konto, aby uniknąć utraty portfela."
         },
         "send_coins":{
            
         },
         "tooltips":{
            "connection_status":{
               
            },
            "balance":{
               
            }
         },
         "receive_money":{
            "anonymous_addresses_description2":"Adresy anonimowe są ważne tylko na jedną transakcję i podlegają opłacie w wysokości 1,5% od przesyłanej kwoty.",
            "sub_header":"Twoje adresy odbiorcze bitcoin",
            "chord_diagram":"Zobacz diagram powiązań",
            "new_address":"Nowy adres",
            "anonymous_addresses":"Adresy anonimowe",
            "archived":"Zarchiwizowane",
            "archived_addresses_description":"Zarchiwizowane adresy może nie trzeba już, że są ukryte w widoku głównym, ale nadal częścią portfela. Możesz rozpakuj je w dowolnym momencie, klikając niebieską ikonę.",
            "new_anonymous_address":"Nowy adres anonimowy",
            "anonymous_addresses_description":"Płatności otrzymane do adresów anonimowych zostaną przekazane innym adresem w portfelu. Wszelkie płatności otrzymane są wysyłane za pomocą miksera izolujący osobistego portfela od nadawcy. Transakcje otrzymane do anonimowych adresów nie mogą być połączone do zwykłego portfela.",
            "new_address_tooltip":"Kliknij tutaj, aby wygenerować nowy adres bitcoin. Możesz rozpocząć odbieranie bitcoins do tego adresu natychmiast"
         },
         "nav":{
            "home":"Portfel główny",
            "send":"Wysyłanie pieniędzy"
         },
         "account_settings":{
            "nav":{
               
            },
            "password_hints_description":" Jeśli zapomnisz hasło (s) wskazówki mogą być przydatne do pobiegać pamięć. Jeśli jest adres e-mail związany z twoich aluzji konta można wysłane. Jeśli nie ma e-mail jest powiązany z kontem wskazówki są dostępne dla każdego, kto zna swój identyfikator portfela."
         },
         "import_export":{
            "rpc":{
               
            },
            "import_wallet_formats":{
               
            }
         },
         "login":{
            
         },
         "wallet_home":{
            "this_is_your_bitcoin_address":"To jest twój główny adres bitcoin"
         },
         "success":{
            
         },
         "modals":{
            "send_payment":"Wyślij płatność",
            "compressed_private_key_p2":"Zalecanym rozwiązaniem do zamiatać funduszy do istniejącego adresu Bitcoin. Chcesz zamiatać klucza prywatnego, a nie?"
         }
      },
      "wallet":{
         "slogan":"Bądź własnym bankiem",
         "start_new":"Utwórz nowy portfel"
      },
      "unconfirmed":{
         
      },
      "hub_nodes":{
         
      },
      "transaction_page":{
         "double_spend":{
            
         }
      },
      "errors":{
         
      },
      "relayed_by":{
         
      },
      "rejected":{
         
      },
      "webgl_globe":{
         
      },
      "error_page":{
         
      },
      "payment_request":{
         
      },
      "propagation":{
         
      },
      "ads":{
         "bitinstant":{
            
         }
      },
      "translations_page":{
         "steps":{
            
         }
      },
      "about_us":{
         
      },
      "wallet_index":{
         "anonymous":{
            
         },
         "merchants":{
            
         },
         "control":{
            
         },
         "slides":{
            
         },
         "easy":{
            
         },
         "try_demo_account":"Przetestuj konto demonstracyjne",
         "confused":{
            
         },
         "tooltips":{
            
         },
         "features":{
            
         },
         "security":{
            "title":"Bezpieczny"
         }
      },
      "tx_tree":{
         
      },
      "push_tx":{
         
      },
      "maintenance":{
         
      },
      "startup_message":{
         
      },
      "emails":{
         "two_factor_reset_request":{
            
         },
         "tx":{
            
         },
         "confirmation_code":{
            
         },
         "password_hints":{
            
         },
         "wallet_backup":{
            
         },
         "welcome":{
            
         },
         "account_locked":{
            
         }
      },
      "blocks":{
         
      },
      "largest_transactions":{
         
      },
      "pools":{
         
      },
      "wallet_new":{
         
      },
      "header":{
         
      },
      "misc":{
         
      },
      "footer":{
         
      },
      "charts":{
         "errors":{
            
         }
      },
      "block_height":{
         
      },
      "strange_transactions":{
         
      },
      "notifications":{
         
      },
      "address":{
         "table_transactions":{
            
         },
         "table_summary":{
            
         }
      },
      "ip_log":{
         
      }
   },
   "code":"pl",
   "properties":{
      "extends":"auto_polish"
   }
}